Quasar/Quasar.py
Quasar/__init__.py
Quasar/example.py
quantum_automated_system_for_advanced_recycling/Quasar.py
quantum_automated_system_for_advanced_recycling/__init__.py
quantum_automated_system_for_advanced_recycling/example.py
quantum_automated_system_for_advanced_recycling-0.2.2.dist-info/METADATA
quantum_automated_system_for_advanced_recycling-0.2.2.dist-info/WHEEL
quantum_automated_system_for_advanced_recycling-0.2.2.dist-info/top_level.txt
quantum_automated_system_for_advanced_recycling-0.2.2.dist-info/RECORD
