Metadata-Version: 2.1
Name: quantum-automated-system-for-advanced-recycling
Version: 0.2.2
Summary: Q.U.A.S.A.R. - Quantum Automated System for Advanced Recycling
Home-page: https://github.com/1mpossible-code/quasar
Keywords: python,quasar,qunatum,convolution,quanvolution
Classifier: Development Status :: 2 - Pre-Alpha
Classifier: Intended Audience :: Education
Classifier: Operating System :: OS Independent
Classifier: License :: OSI Approved :: GNU General Public License v3 (GPLv3)
Classifier: Programming Language :: Python :: 3
Classifier: Programming Language :: Python :: 3.5
Classifier: Programming Language :: Python :: 3.6
Classifier: Programming Language :: Python :: 3.7
Classifier: Programming Language :: Python :: 3.8
Classifier: Programming Language :: Python :: 3.9
Classifier: Programming Language :: Python :: 3.10
Classifier: Programming Language :: Python :: 3.11
Requires-Dist: pennylane ~=0.32.0
Requires-Dist: tensorflow ~=2.13.0
Requires-Dist: Pillow ~=10.0.1
